pyspark-stubs/__init__.pyi
pyspark-stubs/_globals.pyi
pyspark-stubs/_typing.pyi
pyspark-stubs/accumulators.pyi
pyspark-stubs/broadcast.pyi
pyspark-stubs/conf.pyi
pyspark-stubs/context.pyi
pyspark-stubs/daemon.pyi
pyspark-stubs/files.pyi
pyspark-stubs/find_spark_home.pyi
pyspark-stubs/install.pyi
pyspark-stubs/instrumentation_utils.pyi
pyspark-stubs/java_gateway.pyi
pyspark-stubs/join.pyi
pyspark-stubs/profiler.pyi
pyspark-stubs/rdd.pyi
pyspark-stubs/rddsampler.pyi
pyspark-stubs/resultiterable.pyi
pyspark-stubs/serializers.pyi
pyspark-stubs/shell.pyi
pyspark-stubs/shuffle.pyi
pyspark-stubs/statcounter.pyi
pyspark-stubs/status.pyi
pyspark-stubs/storagelevel.pyi
pyspark-stubs/taskcontext.pyi
pyspark-stubs/traceback_utils.pyi
pyspark-stubs/util.pyi
pyspark-stubs/version.pyi
pyspark-stubs/worker.pyi
pyspark-stubs/worker_util.pyi
pyspark-stubs/cloudpickle/__init__.pyi
pyspark-stubs/cloudpickle/cloudpickle.pyi
pyspark-stubs/cloudpickle/cloudpickle_fast.pyi
pyspark-stubs/cloudpickle/compat.pyi
pyspark-stubs/errors/__init__.pyi
pyspark-stubs/errors/error_classes.pyi
pyspark-stubs/errors/utils.pyi
pyspark-stubs/errors/exceptions/__init__.pyi
pyspark-stubs/errors/exceptions/base.pyi
pyspark-stubs/errors/exceptions/captured.pyi
pyspark-stubs/errors/exceptions/connect.pyi
pyspark-stubs/ml/__init__.pyi
pyspark-stubs/ml/base.pyi
pyspark-stubs/ml/classification.pyi
pyspark-stubs/ml/clustering.pyi
pyspark-stubs/ml/common.pyi
pyspark-stubs/ml/dl_util.pyi
pyspark-stubs/ml/evaluation.pyi
pyspark-stubs/ml/feature.pyi
pyspark-stubs/ml/fpm.pyi
pyspark-stubs/ml/functions.pyi
pyspark-stubs/ml/image.pyi
pyspark-stubs/ml/model_cache.pyi
pyspark-stubs/ml/pipeline.pyi
pyspark-stubs/ml/recommendation.pyi
pyspark-stubs/ml/regression.pyi
pyspark-stubs/ml/stat.pyi
pyspark-stubs/ml/tree.pyi
pyspark-stubs/ml/tuning.pyi
pyspark-stubs/ml/util.pyi
pyspark-stubs/ml/wrapper.pyi
pyspark-stubs/ml/connect/__init__.pyi
pyspark-stubs/ml/connect/base.pyi
pyspark-stubs/ml/connect/classification.pyi
pyspark_safestubs-0.1.6.dist-info/METADATA
pyspark_safestubs-0.1.6.dist-info/WHEEL
pyspark_safestubs-0.1.6.dist-info/RECORD
